pretty_yarrrml2rml/__init__.py
pretty_yarrrml2rml/__main__.py
pretty_yarrrml2rml/constants.py
pretty_yarrrml2rml/mapping.py
pretty_yarrrml2rml/predicateobject.py
pretty_yarrrml2rml/source.py
pretty_yarrrml2rml/subject.py
pretty_yarrrml2rml/termmap.py
pretty_yarrrml2rml-0.6.1.dist-info/METADATA
pretty_yarrrml2rml-0.6.1.dist-info/WHEEL
pretty_yarrrml2rml-0.6.1.dist-info/top_level.txt
pretty_yarrrml2rml-0.6.1.dist-info/RECORD
