Metadata-Version: 2.1
Name: pretty-yarrrml2rml
Version: 0.6.1
Summary: The tool translates mapping rules in RML from YARRRML serialization to RDF turtle in a pretty and interpreatable way for humans. The translation is based on RML and YARRRML specifications.
Home-page: https://github.com/oeg-upm/pretty-yarrrml2rml
Author: David Chaves-Fraga
Author-email: david.chaves@upm.es
License: Apache 2.0
Classifier: Programming Language :: Python :: 3
Classifier: License :: OSI Approved :: Apache Software License
Classifier: Operating System :: OS Independent
Classifier: Environment :: Console
Classifier: Intended Audience :: Science/Research
Classifier: Topic :: Utilities
Classifier: Topic :: Software Development :: Pre-processors
Classifier: Topic :: Scientific/Engineering :: Interface Engine/Protocol Translator
Requires-Python: >=3.6
Requires-Dist: pyyaml (==6.0)
Requires-Dist: rdflib (==6.2.0)
